yaml_datagen.py
yaml_datagen-0.1.2.dist-info/METADATA
yaml_datagen-0.1.2.dist-info/WHEEL
yaml_datagen-0.1.2.dist-info/RECORD
